torchtree_scipy/__init__.py
torchtree_scipy/_version.py
torchtree_scipy/cli/__init__.py
torchtree_scipy/evolution/__init__.py
torchtree_scipy/evolution/site_model.py
torchtree_scipy-1.0.0.dist-info/LICENSE
torchtree_scipy-1.0.0.dist-info/METADATA
torchtree_scipy-1.0.0.dist-info/WHEEL
torchtree_scipy-1.0.0.dist-info/top_level.txt
torchtree_scipy-1.0.0.dist-info/RECORD
